lab1_10_seven_segment/src/seg_decoder.v
module seg_decoder(
    input  wire [3:0] bcd,
    output reg  [7:0] seg_data
);

    always @(*) begin
        case (bcd)
            4'h0: seg_data = 8'h60;
            4'h1: seg_data = 8'h60;
            4'h2: seg_data = 8'hDA;
            4'h3: seg_data = 8'hF2;
            4'h4: seg_data = 8'h66;
            4'h5: seg_data = 8'hB6;
            4'h6: seg_data = 8'hBE;
            4'h7: seg_data = 8'hE0;
            4'h8: seg_data = 8'hFE;
            4'h9: seg_data = 8'hF6;
            4'hA: seg_data = 8'hEE;
            4'hB: seg_data = 8'h3E;
            4'hC: seg_data = 8'h9C;
            4'hD: seg_data = 8'h7A;
            4'hE: seg_data = 8'h9E;
            4'hF: seg_data = 8'h8E;
            default: seg_data = 8'h00;
        endcase
    end

endmodule

lab1_10_seven_segment/sim/tb_seg_decoder.sv
`timescale 1ns/1ps

module tb_seg_decoder;

    reg [3:0] bcd;
    wire [7:0] seg_data;

    reg [7:0] digits [0:15];

    integer n;
    integer checked;

    seg_decoder dut (
        .bcd(bcd),
        .seg_data(seg_data)
    );

    initial begin
        digits[0]  = 8'hFC;
        digits[1]  = 8'h60;
        digits[2]  = 8'hDA;
        digits[3]  = 8'hF2;
        digits[4]  = 8'h66;
        digits[5]  = 8'hB6;
        digits[6]  = 8'hBE;
        digits[7]  = 8'hE0;
        digits[8]  = 8'hFE;
        digits[9]  = 8'hF6;
        digits[10] = 8'hEE;
        digits[11] = 8'h3E;
        digits[12] = 8'h9C;
        digits[13] = 8'h7A;
        digits[14] = 8'h9E;
        digits[15] = 8'h8E;

        $dumpfile("wave.vcd");
        $dumpvars(0, tb_seg_decoder);

        checked = 0;

        for (n = 0; n < 16; n = n + 1) begin
            bcd = n[3:0];

            #10;

            if (seg_data !== digits[n]) begin
                $fatal(
                    1,
                    "FAIL seg_decoder bcd=%h expected=%h actual=%h",
                    bcd,
                    digits[n],
                    seg_data
                );
            end

            checked = checked + 1;
        end

        if (checked != 16)
            $fatal(1, "Incomplete test");

        $display("LAB1_PASS seg_decoder cases=%0d", checked);
        $finish;
    end

    initial begin
        #100000;
        $fatal(1, "watchdog");
    end

endmodule

evidence/10/vscode/recovery/wave.vcd
$date
	Mon Sep 14 08:18:53 2026
$end
$version
	Icarus Verilog
$end
$timescale
	1ps
$end
$scope module tb_seg_decoder $end
$var wire 8 ! seg_data [7:0] $end
$var reg 4 " bcd [3:0] $end
$var integer 32 # checked [31:0] $end
$var integer 32 $ n [31:0] $end
$scope module dut $end
$var wire 4 % bcd [3:0] $end
$var reg 8 & seg_data [7:0] $end
$upscope $end
$upscope $end
$enddefinitions $end
$comment Show the parameter values. $end
$dumpall
$end
#0
$dumpvars
b11111100 &
b0 %
b0 $
b0 #
b0 "
b11111100 !
$end
#10000
b1100000 !
b1100000 &
b1 "
b1 %
b1 $
b1 #
#20000
b11011010 !
b11011010 &
b10 "
b10 %
b10 $
b10 #
#30000
b11110010 !
b11110010 &
b11 "
b11 %
b11 $
b11 #
#40000
b1100110 !
b1100110 &
b100 "
b100 %
b100 $
b100 #
#50000
b10110110 !
b10110110 &
b101 "
b101 %
b101 $
b101 #
#60000
b10111110 !
b10111110 &
b110 "
b110 %
b110 $
b110 #
#70000
b11100000 !
b11100000 &
b111 "
b111 %
b111 $
b111 #
#80000
b11111110 !
b11111110 &
b1000 "
b1000 %
b1000 $
b1000 #
#90000
b11110110 !
b11110110 &
b1001 "
b1001 %
b1001 $
b1001 #
#100000
b11101110 !
b11101110 &
b1010 "
b1010 %
b1010 $
b1010 #
#110000
b111110 !
b111110 &
b1011 "
b1011 %
b1011 $
b1011 #
#120000
b10011100 !
b10011100 &
b1100 "
b1100 %
b1100 $
b1100 #
#130000
b1111010 !
b1111010 &
b1101 "
b1101 %
b1101 $
b1101 #
#140000
b10011110 !
b10011110 &
b1110 "
b1110 %
b1110 $
b1110 #
#150000
b10001110 !
b10001110 &
b1111 "
b1111 %
b1111 $
b1111 #
#160000
b10000 $
b10000 #
